ondewo/__init__.py
ondewo/csi/__init__.py
ondewo/csi/conversation_pb2.py
ondewo/csi/conversation_pb2.pyi
ondewo/csi/conversation_pb2_grpc.py
ondewo/csi/client/__init__.py
ondewo/csi/client/client.py
ondewo/csi/client/client_config.py
ondewo/csi/client/services_container.py
ondewo/csi/client/services/__init__.py
ondewo/csi/client/services/conversations.py
ondewo_csi_client-5.2.0.dist-info/LICENSE
ondewo_csi_client-5.2.0.dist-info/METADATA
ondewo_csi_client-5.2.0.dist-info/WHEEL
ondewo_csi_client-5.2.0.dist-info/top_level.txt
ondewo_csi_client-5.2.0.dist-info/RECORD
