Metadata-Version: 2.1
Name: ondewo-csi-client
Version: 5.2.0
Summary: ONDEWO Communication System Integration (CSI) Client library for Python
Home-page: https://github.com/ondewo/ondewo-csi-client-python
Author: ONDEWO GmbH
Author-email: office@ondewo.com
Classifier: Development Status :: 5 - Production/Stable
Classifier: Intended Audience :: Developers
Classifier: License :: OSI Approved :: Apache Software License
Classifier: Operating System :: OS Independent
Classifier: Programming Language :: Python :: 3.9
Classifier: Programming Language :: Python :: 3.10
Classifier: Programming Language :: Python :: 3.11
Classifier: Programming Language :: Python :: 3.12
Classifier: Topic :: Software Development :: Libraries
Requires-Python: >=3
License-File: LICENSE
Requires-Dist: dataclasses-json
Requires-Dist: google-api-core
Requires-Dist: googleapis-common-protos
Requires-Dist: grpcio-reflection
Requires-Dist: grpcio-tools
Requires-Dist: grpcio
Requires-Dist: numpy
Requires-Dist: ondewo-client-utils
Requires-Dist: ondewo-logging
Requires-Dist: setuptools
